MANIFEST.in
README.md
setup.cfg
setup.py
juspark/__init__.py
juspark/exceptions.py
juspark/magics.py
juspark/output.py
juspark/parsers.py
juspark/spark.py
juspark.egg-info/PKG-INFO
juspark.egg-info/SOURCES.txt
juspark.egg-info/dependency_links.txt
juspark.egg-info/top_level.txt