Metadata-Version: 1.0
Name: juspark
Version: 0.0.2a1
Summary: Simple magics to run pyspark direclty from jupyter
Home-page: https://github.com/piotrszul/pyrander
Author: Piotr Szul
Author-email: piotr.szul@csiro.au
License: MIT
Keywords: testing,logging,example
Platform: UNKNOWN
